Workbook

Sheet 费率表
B2: 先选择下面站点↓ | C2: 计算公式：（原价*折扣价）-（原价*折扣价*平台费率）-国际物流成本-货代成本-优惠卷（官方优惠卷或者店铺自己设置优惠卷）-货品成本 公告：近期泰国站点新增了关税、服饰类目最高30的税率、已经上架的商品可以去调整折扣比例拉高折后价，去抵消关税的成本、新上架的商品可以在妙手定价模版填入对应类目的关税比例，此表默认预填服饰类目30%。
A3: 选择站点→ | B3: 越南=VND
B5: 注意：切换站点只是改变汇率公式、右边实际内容数值需自己更改填入 | C5: 类型 | D5: 本地展示价（原价） （在商品管理查看） | E5: 折扣范围（1-10） (折扣7折则填7） （未打折则填10) | F5: 泰国关税 （下面自动填写） 修改去下面费率列表 | G5: 平台费率 （下面自动填写） 修改去下面费率列表 | H5: 填商品重量（头程运费）（单位g）1KG=1000g 1000g=2斤 | I5: 可以加入其他成本 如货代成本（元） | J5: 其他优惠卷或者店铺自己设置优惠卷（当地货币） | K5: 货品成本（填人民币） （商品采集价） | M5: 预估利润
C6: 右边填入数值→ | D6: 340000 | E6: 5 | F6: =IF(TRIM(UPPER(B3))="泰国=THB",E38,"0") -> 0 | G6: =VLOOKUP(B3,$L:$M,2,FALSE) -> 0.29 | H6: 400 | I6: 2 | J6: 0 | K6: 0 | M6: =D9*E9-F9-G9-H9-I9-J9-K9 -> 17.647554
D8: 人民币 | E8: 折扣 | G8: 人民币 | H8: 人民币 | I8: 人民币 | J8: 人民币 | K8: 人民币
B9: V:lichen5728 | C9: 自动转换人民币 （无需填写）→ | D9: =D6/VLOOKUP(B3,$C:$D,2,FALSE) -> 89.426618 | E9: =E6/10 -> 0.5 | F9: =(D9*E9/(1+F6))*F6 -> 0 | G9: =(D9*E9-F9)*G6 -> 12.96686 | H9: =(VLOOKUP(B3,$G:$H,2,FALSE))/VLOOKUP(B3,$C:$D,2,FALSE) -> 12.098895 | I9: =I6 -> 2 | J9: =J6/VLOOKUP(B3,$C:$D,2,FALSE) -> 0 | K9: =K6 -> 0 | M9: 当地站点货币
C10: 自动转换当地货币 （无需填写）→ | D10: =D6 -> 340000 | E10: =D10*E9 -> 170000 | F10: =(D6*E9/(1+F6))*F6 -> 0 | G10: =(D6*E9-F10)*G6 -> 49300 | H10: =(VLOOKUP(B3,$G:$H,2,FALSE)) -> 46000 | I10: =I9*VLOOKUP(B3,$C:$D,2,FALSE) -> 7604 | J10: =J6 -> 0 | K10: =K9*VLOOKUP(B3,$C:$D,2,FALSE) -> 0 | M10: =D10*E9-F10-G10-H10-I10-J10-K10 -> 67096
B12: 请注意：此工具计算预估结果仅做参考，（因此汇率换算会和实时有差异、物流价卡请留意TK变动、平台佣金以及各种税费会因类目之间不同有不同的占比、请根据所属类目进行调整、以TK最新公告税率为准）
B15: 1元换算各国站点金额（可根据实时汇率手动进行修改） | G15: 国际物流成本价卡（头程费用）
B16: 人民币 | C16: 站点汇率 | D16: 汇率公式（可更改） | G16: 站点 | H16: 当地货币计算结果 | I16: 重量(克) | J16: 首重(当地货币) | K16: 续重（当地货币） | L16: 买家尾程运费
B17: 1人民币=人民币 | C17: 中国=CNY | D17: 1
B18: 1人民币=美元 | C18: 美国=＄ | D18: =(1/7.2) -> 0.13888889
B19: 1人民币=越南盾 | C19: 越南=VND | D19: 3802 | G19: 越南=VND | H19: =J19+((H6-I19)/10*K19) -> 46000 | I19: 10 | J19: 10900 | K19: 900 | L19: 30000
B20: 1人民币=泰铢 | C20: 泰国=THB | D20: 4.7 | G20: 泰国=THB | H20: =J20+((H6-I20)/10*K20) -> 40 | I20: 10 | J20: 1 | K20: 1 | L20: 79
B21: 1人民币=马来币 | C21: 马来=MYR | D21: =(1/1.69) -> 0.59171598 | G21: 马来=MYR | H21: =J21+((H6-I21)/10*K21) -> 6 | I21: 10 | J21: 0.15 | K21: 0.15 | L21: 10
B22: 1人民币=菲律宾 | C22: 菲律宾=PHP | D22: 8.65 | G22: 菲律宾=PHP | H22: =J22+((H6-I22)/10*K22) -> 180 | I22: 10 | J22: 4.5 | K22: 4.5 | L22: 40
B23: 1人民币=新加坡 | C23: 新加坡=SGD | D23: =(1/5.45) -> 0.18348624 | G23: 新加坡=SGD | H23: =J23+((H6-I23)/10*K23) -> 6.38 | I23: 40 | J23: 0.98 | K23: 0.15 | L23: 60
B25: 平台费率列表，下面可修改（泰国关税女装预设30） | G25: （平台费率TK会更新，请根据类目以TK实际变动进行调整）
B26: 平台费率 根据自己类目修改 | C26: 越南 | D26: 马来 | E26: 泰国 | G26: 菲律宾 | H26: 新加坡 | L26: 站点 | M26: 合计
B27: 平台佣金费率 | C27: 0.13 | D27: 0.1458 | E27: 0.0856 | G27: 0.068 | H27: 0.0327 | L27: 越南=VND | M27: =(C27+C28+C29+C30+C31+C32+C33+C34+C35+C36) -> 0.29
B28: 交易手续费率 | C28: 0.05 | D28: 0.0378 | E28: 0.0321 | G28: 0.0224 | H28: 0.0218 | L28: 马来=MYR | M28: =(D27+D28+D29+D30+D31+D32+D33+D34+D35+D36) -> 0.2936
B29: 增值税率 | C29: 0.1 | D29: 0.1 | E29: 0.07 | L29: 泰国=THB | M29: =(E27+E28+E30+E31+E32+E33+E34+E35+E36) -> 0.1942
B30: 提现手续费率 | C30: 0.01 | D30: 0.01 | E30: 0.01 | G30: 0.01 | H30: 0.01 | L30: 菲律宾=PHP | M30: =(G27+G28+G29+G30+G31+G32+G33+G34+G35+G36) -> 0.1554
B31: SFP服务费率 | L31: 新加坡=SGD | M31: =(H27+H28+H29+H30+H31+H32+H33+H34+H35+H36) -> 0.1545
B32: 达人佣金费率
B33: 平台基础设施费（泰国） | E33: 0.0023
B34: 电商增长服务费率（泰国） | E34: 0.0642
B35: 包邮服务费（菲律宾） | G35: 0.055
B36: 消费税率（新加坡） | H36: 0.09
B37: 关税（泰国） | E37: 0.3
B38: 关税（泰国补贴后） 填入关税和增值税后自动计算 | E38: =(1+E37*0.8)*(1+E29)-1 -> 0.3268
F39: 以上填入各类费率数值请在后面加上“%”符号

Sheet 跨境物流计算
A1: 跨境物流成本计算工具 | E1: 填入商品重量（克）
E2: 400
A4: 1. 将产品重量填入上面“商品重量”一栏中 2. 相应市场的跨境物流成本将自动展示在右侧表格 3. 请注意：此工具计算结果仅做参考，实际订单可能会出现一单多件、汇率换算差额、包裹重量不符的情况，因此会有差异 4. 跨境物流价卡可能会有变动，请注意TK变更通知 | E4: （当地货币）
E5: 泰国=THB | F5: 越南=VND | G5: 马来=MYR | H5: 菲律宾=PHP | I5: 新加坡=SGD
E6: =E20 -> 40 | F6: =E19 -> 46000 | G6: =E21 -> 6 | H6: =E22 -> 180 | I6: =E23 -> 6.38
E8: （人民币）
E9: 泰国=THB | F9: 越南=VND | G9: 马来=MYR | H9: 菲律宾=PHP | I9: 新加坡=SGD
E10: =(VLOOKUP(E9,$D:$E,2,FALSE))/VLOOKUP(E9,$B:$C,2,FALSE) -> 8.5106383 | F10: =(VLOOKUP(F9,$D:$E,2,FALSE))/VLOOKUP(F9,$B:$C,2,FALSE) -> 12.098895 | G10: =(VLOOKUP(G9,$D:$E,2,FALSE))/VLOOKUP(G9,$B:$C,2,FALSE) -> 10.14 | H10: =(VLOOKUP(H9,$D:$E,2,FALSE))/VLOOKUP(H9,$B:$C,2,FALSE) -> 20.809249 | I10: =(VLOOKUP(I9,$D:$E,2,FALSE))/VLOOKUP(I9,$B:$C,2,FALSE) -> 34.771
A12: 注：以上计算公式都是根据下面汇率金额为基础进行预估计算，可查询资料后手动更新下面“汇率”，“注”(因汇率换算时差、小数精度、等原因，预估结果会有差异) 此工具计算结果仅供参考
A15: 人民币换算各国站点金额 | D15: 跨境物流成本价卡（头程费用）
A16: 人民币 | B16: 站点汇率 | C16: 汇率公式（可更改） | D16: 站点 | E16: 当地货币计算结果 | F16: 起重重量(克) | G16: 首重(当地货币) | H16: 续重（当地货币）
A17: 1人民币=人民币 | B17: 中国=CNY | C17: =费率表!D17 -> 1
A18: 1人民币=美元 | B18: 美国=＄ | C18: =费率表!D18 -> 0.13888889
A19: 1人民币=越南盾 | B19: 越南=VND | C19: =费率表!D19 -> 3802 | D19: 越南=VND | E19: =G19+((E2-F19)/10*H19) -> 46000 | F19: 10 | G19: 10900 | H19: 900
A20: 1人民币=泰铢 | B20: 泰国=THB | C20: =费率表!D20 -> 4.7 | D20: 泰国=THB | E20: =G20+((E2-F20)/10*H20) -> 40 | F20: 10 | G20: 1 | H20: 1
A21: 1人民币=马来币 | B21: 马来=MYR | C21: =费率表!D21 -> 0.59171598 | D21: 马来=MYR | E21: =G21+((E2-F21)/10*H21) -> 6 | F21: 10 | G21: 0.15 | H21: 0.15
A22: 1人民币=菲律宾 | B22: 菲律宾=PHP | C22: =费率表!D22 -> 8.65 | D22: 菲律宾=PHP | E22: =G22+((E2-F22)/10*H22) -> 180 | F22: 10 | G22: 4.5 | H22: 4.5
A23: 1人民币=新加坡 | B23: 新加坡=SGD | C23: =费率表!D23 -> 0.18348624 | D23: 新加坡=SGD | E23: =G23+((E2-F23)/10*H23) -> 6.38 | F23: 40 | G23: 0.98 | H23: 0.15
